ccb_extras/__init__.py
ccb_extras/crypto.py
ccb_extras/py.typed
ccb_extras/ram_disk.py
ccb_extras/yaml.py
ccb_extras-1.1.1.dist-info/METADATA
ccb_extras-1.1.1.dist-info/WHEEL
ccb_extras-1.1.1.dist-info/licenses/LICENSE
ccb_extras-1.1.1.dist-info/RECORD
