Metadata-Version: 2.4
Name: ccb-extras
Version: 1.1.1
Summary: Extra tools for Python 3.
Project-URL: Repository, https://github.com/clydecbrown/ccb-extras
Author-email: Clyde C Brown <clyde.c.brown@pm.me>
License: MIT
License-File: LICENSE
Keywords: encryption,ram disk,utilities,yaml
Classifier: Development Status :: 5 - Production/Stable
Classifier: Intended Audience :: Developers
Classifier: License :: OSI Approved :: MIT License
Classifier: Natural Language :: English
Classifier: Operating System :: OS Independent
Classifier: Programming Language :: Python :: 3.10
Classifier: Programming Language :: Python :: 3.11
Classifier: Programming Language :: Python :: 3.12
Classifier: Programming Language :: Python :: 3.13
Classifier: Programming Language :: Python :: 3.14
Classifier: Topic :: Software Development :: Libraries :: Python Modules
Classifier: Topic :: Utilities
Classifier: Typing :: Typed
Requires-Python: >=3.10
Requires-Dist: ccb-essentials>=1.2.0
Requires-Dist: humanfriendly>=9.1
Requires-Dist: ruamel-yaml>=0.18.5
